{
  "schema_version": 1,
  "run": {
    "id": "full-3",
    "generated_at": "2026-06-11T19:01:43.815Z",
    "cortex_version": "2.0.19"
  },
  "repo": {
    "key": "nodebb__nodebb",
    "name": "NodeBB/NodeBB",
    "url": "https://github.com/NodeBB/NodeBB.git",
    "sha": "55ae053f843f9d500c86e9860d555096520281e1",
    "languages": [
      "javascript"
    ],
    "benches": [
      "Pro"
    ],
    "instances": 11
  },
  "runs": [
    {
      "schema_version": 1,
      "repo": {
        "key": "nodebb__nodebb",
        "name": "NodeBB/NodeBB",
        "url": "https://github.com/NodeBB/NodeBB.git",
        "sha": "55ae053f843f9d500c86e9860d555096520281e1",
        "languages": [
          "javascript"
        ],
        "benches": [
          "Pro"
        ],
        "instances": 11
      },
      "run": {
        "embed_model": "Xenova/all-MiniLM-L6-v2",
        "cortex_version": "2.0.19",
        "run_id": "full-3",
        "started_at": "2026-06-11T17:51:17.473Z",
        "status": "ok",
        "error": null,
        "extracted_at": "2026-06-11T17:57:29.879Z"
      },
      "workspace": {
        "tracked_files": 5722,
        "tracked_bytes": 19875099,
        "detected_source_paths": [
          ".github",
          ".tx",
          "install",
          "public",
          "src",
          "test",
          "types",
          ".codeclimate.yml",
          ".mocharc.yml",
          "app.js",
          "CHANGELOG.md",
          "commitlint.config.js",
          "docker-compose-pgsql.yml",
          "docker-compose-redis.yml",
          "docker-compose.yml",
          "eslint.config.mjs",
          "Gruntfile.js",
          "loader.js",
          "nodebb-global.js",
          "renovate.json",
          "require-main.js",
          "webpack.common.js",
          "webpack.dev.js",
          "webpack.installer.js",
          "webpack.prod.js",
          ".context/notes",
          ".context/decisions",
          "README.md"
        ]
      },
      "timings_ms": {
        "deps": 1127,
        "ingest": 4038,
        "embed": 336530,
        "graph_load": 24634,
        "status": 1528,
        "total": 367858
      },
      "ingest": {
        "mode": "full",
        "counts": {
          "files": 5352,
          "adrs": 0,
          "rules": 5,
          "chunks": 1816,
          "relations_constrains": 1568,
          "relations_implements": 1210,
          "relations_supersedes": 0,
          "relations_defines": 1816,
          "relations_calls": 820,
          "relations_imports": 1291,
          "relations_calls_sql": 0,
          "relations_uses_config_key": 0,
          "relations_uses_resource_key": 0,
          "relations_uses_setting_key": 0,
          "modules": 621,
          "relations_contains": 5243,
          "relations_contains_module": 510,
          "relations_exports": 71,
          "projects": 0,
          "relations_includes_file": 0,
          "relations_references_project": 0,
          "relations_uses_resource": 0,
          "relations_uses_setting": 0,
          "relations_uses_config": 0,
          "relations_transforms_config": 0
        },
        "skipped": {
          "unsupported": 347,
          "tooLarge": 0,
          "binary": 0
        },
        "parser_health": {}
      },
      "files": {
        "total": 5352,
        "by_kind": {
          "DOC": 4433,
          "CODE": 919
        }
      },
      "chunks": {
        "total": 1816,
        "exported": 73,
        "by_kind": {
          "function": 1715,
          "const": 96,
          "class": 2,
          "method": 3
        },
        "by_language": {
          "javascript": {
            "count": 1816,
            "lines": {
              "count": 1816,
              "min": 1,
              "max": 282,
              "mean": 19.32,
              "histogram": [
                {
                  "label": "1-10",
                  "min": 1,
                  "max": 10,
                  "count": 784
                },
                {
                  "label": "11-20",
                  "min": 11,
                  "max": 20,
                  "count": 487
                },
                {
                  "label": "21-40",
                  "min": 21,
                  "max": 40,
                  "count": 342
                },
                {
                  "label": "41-80",
                  "min": 41,
                  "max": 80,
                  "count": 173
                },
                {
                  "label": "81-160",
                  "min": 81,
                  "max": 160,
                  "count": 27
                },
                {
                  "label": "161-320",
                  "min": 161,
                  "max": 320,
                  "count": 3
                },
                {
                  "label": "321+",
                  "min": 321,
                  "max": null,
                  "count": 0
                }
              ],
              "p25": 7,
              "p50": 12,
              "p75": 24.25,
              "p90": 43,
              "p99": 91.7
            },
            "chars": {
              "count": 1816,
              "min": 18,
              "max": 8718,
              "mean": 609.15,
              "histogram": [
                {
                  "label": "0-200",
                  "min": 0,
                  "max": 200,
                  "count": 415
                },
                {
                  "label": "201-500",
                  "min": 201,
                  "max": 500,
                  "count": 680
                },
                {
                  "label": "501-1000",
                  "min": 501,
                  "max": 1000,
                  "count": 409
                },
                {
                  "label": "1001-2000",
                  "min": 1001,
                  "max": 2000,
                  "count": 238
                },
                {
                  "label": "2001-4000",
                  "min": 2001,
                  "max": 4000,
                  "count": 65
                },
                {
                  "label": "4001-8000",
                  "min": 4001,
                  "max": 8000,
                  "count": 8
                },
                {
                  "label": "8001-12000",
                  "min": 8001,
                  "max": 12000,
                  "count": 1
                },
                {
                  "label": "12001+",
                  "min": 12001,
                  "max": null,
                  "count": 0
                }
              ],
              "p25": 213,
              "p50": 384,
              "p75": 769.25,
              "p90": 1320.5,
              "p99": 2947.9
            }
          }
        },
        "lines": {
          "count": 1816,
          "min": 1,
          "max": 282,
          "mean": 19.32,
          "histogram": [
            {
              "label": "1-10",
              "min": 1,
              "max": 10,
              "count": 784
            },
            {
              "label": "11-20",
              "min": 11,
              "max": 20,
              "count": 487
            },
            {
              "label": "21-40",
              "min": 21,
              "max": 40,
              "count": 342
            },
            {
              "label": "41-80",
              "min": 41,
              "max": 80,
              "count": 173
            },
            {
              "label": "81-160",
              "min": 81,
              "max": 160,
              "count": 27
            },
            {
              "label": "161-320",
              "min": 161,
              "max": 320,
              "count": 3
            },
            {
              "label": "321+",
              "min": 321,
              "max": null,
              "count": 0
            }
          ],
          "p25": 7,
          "p50": 12,
          "p75": 24.25,
          "p90": 43,
          "p99": 91.7
        },
        "chars": {
          "count": 1816,
          "min": 18,
          "max": 8718,
          "mean": 609.15,
          "histogram": [
            {
              "label": "0-200",
              "min": 0,
              "max": 200,
              "count": 415
            },
            {
              "label": "201-500",
              "min": 201,
              "max": 500,
              "count": 680
            },
            {
              "label": "501-1000",
              "min": 501,
              "max": 1000,
              "count": 409
            },
            {
              "label": "1001-2000",
              "min": 1001,
              "max": 2000,
              "count": 238
            },
            {
              "label": "2001-4000",
              "min": 2001,
              "max": 4000,
              "count": 65
            },
            {
              "label": "4001-8000",
              "min": 4001,
              "max": 8000,
              "count": 8
            },
            {
              "label": "8001-12000",
              "min": 8001,
              "max": 12000,
              "count": 1
            },
            {
              "label": "12001+",
              "min": 12001,
              "max": null,
              "count": 0
            }
          ],
          "p25": 213,
          "p50": 384,
          "p75": 769.25,
          "p90": 1320.5,
          "p99": 2947.9
        }
      },
      "embeddings": {
        "model": "Xenova/all-MiniLM-L6-v2",
        "dimensions": 384,
        "mode": "full",
        "counts": {
          "entities": 7794,
          "output": 7794,
          "embedded": 7794,
          "reused": 0,
          "failed": 0
        },
        "by_entity_type": {
          "Chunk": 1816,
          "File": 5352,
          "Module": 621,
          "Rule": 5
        },
        "throughput_per_s": 23.16
      },
      "graph": {
        "nodes": {
          "files": 5352,
          "chunks": 1816,
          "rules": 5,
          "adrs": 0,
          "modules": 621,
          "projects": 0
        },
        "edges": {
          "total": 12529,
          "by_type": {
            "CALLS": 820,
            "CALLS_SQL": 0,
            "CONSTRAINS": 1568,
            "CONTAINS": 5243,
            "CONTAINS_MODULE": 510,
            "DEFINES": 1816,
            "EXPORTS": 71,
            "IMPLEMENTS": 1210,
            "IMPORTS": 1291,
            "INCLUDES_FILE": 0,
            "REFERENCES_PROJECT": 0,
            "SUPERSEDES": 0,
            "TRANSFORMS_CONFIG": 0,
            "USES_CONFIG": 0,
            "USES_CONFIG_KEY": 0,
            "USES_RESOURCE": 0,
            "USES_RESOURCE_KEY": 0,
            "USES_SETTING": 0,
            "USES_SETTING_KEY": 0
          }
        },
        "chunk_connectivity": {
          "chunk_chunk_edges": 820,
          "avg_degree": 0.9,
          "max_degree": 9,
          "isolated_count": 891,
          "isolated_pct": 49.06,
          "degree": {
            "count": 1816,
            "min": 0,
            "max": 9,
            "mean": 0.9,
            "histogram": [
              {
                "label": "0",
                "min": 0,
                "max": 0,
                "count": 891
              },
              {
                "label": "1",
                "min": 1,
                "max": 1,
                "count": 544
              },
              {
                "label": "2",
                "min": 2,
                "max": 2,
                "count": 197
              },
              {
                "label": "3-4",
                "min": 3,
                "max": 4,
                "count": 149
              },
              {
                "label": "5-8",
                "min": 5,
                "max": 8,
                "count": 33
              },
              {
                "label": "9-16",
                "min": 9,
                "max": 16,
                "count": 2
              },
              {
                "label": "17-32",
                "min": 17,
                "max": 32,
                "count": 0
              },
              {
                "label": "33+",
                "min": 33,
                "max": null,
                "count": 0
              }
            ],
            "p25": 0,
            "p50": 1,
            "p75": 1,
            "p90": 3,
            "p99": 6
          },
          "top_connected": [
            {
              "id": "chunk:public/src/client/category/tools.js:getTopicEl:267-269",
              "degree": 9
            },
            {
              "id": "chunk:public/src/client/topic/postTools.js:addPostHandlers:92-283",
              "degree": 9
            },
            {
              "id": "chunk:public/src/client/post-queue.js:handleActions:274-357",
              "degree": 8
            },
            {
              "id": "chunk:src/user/profile.js:validateData:79-88",
              "degree": 8
            },
            {
              "id": "chunk:public/src/installer/install.js:activate:105-171",
              "degree": 7
            },
            {
              "id": "chunk:public/src/modules/api.js:call:8-32",
              "degree": 7
            },
            {
              "id": "chunk:public/src/modules/navigator.js:handleScrollNav:208-356",
              "degree": 7
            },
            {
              "id": "chunk:src/middleware/render.js:renderHeaderFooter:384-400",
              "degree": 7
            },
            {
              "id": "chunk:public/src/client/topic/postTools.js:onQuoteClicked:320-339",
              "degree": 6
            },
            {
              "id": "chunk:public/src/modules/alerts.js:alert:6-18",
              "degree": 6
            }
          ]
        }
      },
      "parse_errors": 0
    }
  ]
}
